yzhanurlparser/__init__.py
yzhanurlparser/data/IP2LOCATION-LITE-DB1.BIN
yzhanurlparser/lib/__init__.py
yzhanurlparser/lib/ip.py
yzhanurlparser/lib/url.py
yzhanurlparser-0.1.0.dist-info/LICENSE
yzhanurlparser-0.1.0.dist-info/METADATA
yzhanurlparser-0.1.0.dist-info/WHEEL
yzhanurlparser-0.1.0.dist-info/top_level.txt
yzhanurlparser-0.1.0.dist-info/RECORD
