Metadata-Version: 2.1
Name: yzhanurlparser
Version: 0.1.0
Summary: A python library which could parse URL to ip and country.
Home-page: https://github.com/mantoufan/yzhanurlparser
Author: mantoufan
Author-email: mhjlw@126.com
Classifier: Programming Language :: Python :: 3
Classifier: License :: OSI Approved :: MIT License
Classifier: Operating System :: OS Independent
Requires-Python: >=3.6
License-File: LICENSE
Requires-Dist: IP2Location
